cana/__init__.py
cana/constants.py
cana/convolution.py
cana/exceptions.py
cana/photo.py
cana/photoconfig.py
cana/spec.py
cana/specdata.py
cana/util.py
cana/composition/__init__.py
cana/composition/constants.py
cana/composition/core.py
cana/composition/mixtures.py
cana/composition/randomsearch.py
cana/composition/shkuratov.py
cana/datasets/__init__.py
cana/datasets/specdata.py
cana/datasets/data/photometry/2mass/2mass.tab
cana/datasets/data/photometry/ecas/ecas
cana/datasets/data/photometry/jplus/jplus.tab
cana/datasets/data/photometry/jwst/jwst.tab
cana/datasets/data/photometry/osiris/osiris.tab
cana/datasets/data/photometry/sdss/sdss.tab
cana/datasets/data/photometry/spitzer/spitzer.tab
cana/datasets/data/taxonomy/bus_demeo.tab
cana/datasets/data/testdata/spectra/primass/000334.tab
cana/datasets/data/testdata/spectra/primass/000752.tab
cana/datasets/data/testdata/spectra/primass/000752b.tab
cana/datasets/data/testdata/spectra/primass/001144.tab
cana/datasets/data/testdata/spectra/primass/001269.tab
cana/datasets/data/testdata/spectra/primass/001439.tab
cana/datasets/data/testdata/spectra/primass/001902.tab
cana/datasets/data/testdata/spectra/primass/003202.tab
cana/datasets/data/testdata/spectra/primass/003577.tab
cana/datasets/data/testdata/spectra/primass/003843.tab
cana/datasets/data/testdata/spectra/primass/007394.tab
cana/pipelines/__init__.py
cana/pipelines/specpipes.py
cana/spectools/__init__.py
cana/spectools/slopetool.py
cana/spectools/specband.py
cana/spectools/taxonomytool.py
cana/spectools/uncertainties.py
cana/thermal/__init__.py
cana/thermal/core.py
cana/thermal/models.py
cana_asteroids-0.2.1.dist-info/LICENSE
cana_asteroids-0.2.1.dist-info/METADATA
cana_asteroids-0.2.1.dist-info/WHEEL
cana_asteroids-0.2.1.dist-info/top_level.txt
cana_asteroids-0.2.1.dist-info/RECORD
